mymodule/__init__.py
mymodule/functions.py
deploymentPackageTesting-1.0.5.dist-info/METADATA
deploymentPackageTesting-1.0.5.dist-info/WHEEL
deploymentPackageTesting-1.0.5.dist-info/top_level.txt
deploymentPackageTesting-1.0.5.dist-info/RECORD
